d2lapi/D2L_Widgets.py
d2lapi/Final_Quiz.py
d2lapi/Final_Survey.py
d2lapi/Visualization_Bar.py
d2lapi/__init__.py
test/.gitkeep
test/__init__.py
test/test_cases_quiz.py
test/test_cases_survey.py
d2lapi-0.3.0.dist-info/LICENSE
d2lapi-0.3.0.dist-info/METADATA
d2lapi-0.3.0.dist-info/WHEEL
d2lapi-0.3.0.dist-info/top_level.txt
d2lapi-0.3.0.dist-info/RECORD
